<Properties StartupConfiguration="{F5D53BF1-1D3C-4ACA-B34E-1DA33EA49C10}|Default">
  <MonoDevelop.Ide.ItemProperties.RedisDemo PreferredExecutionTarget="/Applications/Safari.app" />
  <MonoDevelop.Ide.Workbench>
    <Pads>
      <Pad Id="ProjectPad">
        <State name="__root__">
          <Node name="RedisDemoApp" expanded="True" />
        </State>
      </Pad>
    </Pads>
  </MonoDevelop.Ide.Workbench>
  <MonoDevelop.Ide.DebuggingService.PinnedWatches />
  <MonoDevelop.Ide.Workspace ActiveConfiguration="Debug" />
  <MonoDevelop.Ide.DebuggingService.Breakpoints>
    <BreakpointStore />
  </MonoDevelop.Ide.DebuggingService.Breakpoints>
  <MultiItemStartupConfigurations />
</Properties>